stem_splitter/band_split_roformer.py
stem_splitter/cli.py
stem_splitter/inference.py
stem_splitter/transformer.py
stem_splitter-0.0.3.dist-info/METADATA
stem_splitter-0.0.3.dist-info/WHEEL
stem_splitter-0.0.3.dist-info/entry_points.txt
stem_splitter-0.0.3.dist-info/top_level.txt
stem_splitter-0.0.3.dist-info/RECORD
