Metadata-Version: 2.4
Name: stem-splitter
Version: 0.0.3
Summary: Simple, readable audio stem separation library
Author: anime-song
License: MIT
Requires-Python: >=3.10
Requires-Dist: numpy>=1.24.1
Requires-Dist: tqdm>=4.66
Requires-Dist: librosa
Requires-Dist: einops>=0.7
Requires-Dist: torch>=2.7.0
Requires-Dist: torchaudio>=2.7.0
Requires-Dist: torchcodec
